dasty_api/ScenarioRunner.py
dasty_api/Step.py
dasty_api/YAMLScenario.py
dasty_api/__init__.py
dasty_api/utils.py
examples/__init__.py
examples/scenario_runner.py
examples/simple_server.py
tests/__init__.py
tests/test_scenario_runner.py
tests/test_utils.py
dasty_api-0.4.0.dist-info/LICENSE
dasty_api-0.4.0.dist-info/METADATA
dasty_api-0.4.0.dist-info/WHEEL
dasty_api-0.4.0.dist-info/top_level.txt
dasty_api-0.4.0.dist-info/RECORD
