Metadata-Version: 2.1
Name: dasty_api
Version: 0.4.0
Summary: Declarative API Scenario Testing in YAML - Easily define and run API tests using YAML.
Home-page: https://github.com/rohitkochhar/dasty
Author: Rohit Singh
Author-email: rsingh.yaml@gmail.com
Classifier: Programming Language :: Python :: 3
Classifier: License :: OSI Approved :: MIT License
Classifier: Operating System :: OS Independent
Requires-Python: >=3.6
License-File: LICENSE
Requires-Dist: certifi ==2023.11.17
Requires-Dist: charset-normalizer ==3.3.2
Requires-Dist: idna ==3.6
Requires-Dist: PyYAML ==6.0.1
Requires-Dist: requests ==2.31.0
Requires-Dist: urllib3 ==2.1.0
